pydivkit/__init__.py
pydivkit/core/__init__.py
pydivkit/core/compat.py
pydivkit/core/entities.py
pydivkit/core/fields.py
pydivkit/core/types/__init__.py
pydivkit/core/types/union.py
pydivkit/div/__init__.py
pydivkit/div/array_value.py
pydivkit/div/array_variable.py
pydivkit/div/boolean_value.py
pydivkit/div/boolean_variable.py
pydivkit/div/color_value.py
pydivkit/div/color_variable.py
pydivkit/div/content_text.py
pydivkit/div/content_url.py
pydivkit/div/dict_value.py
pydivkit/div/dict_variable.py
pydivkit/div/div.py
pydivkit/div/div_absolute_edge_insets.py
pydivkit/div/div_accessibility.py
pydivkit/div/div_action.py
pydivkit/div/div_action_animator_start.py
pydivkit/div/div_action_animator_stop.py
pydivkit/div/div_action_array_insert_value.py
pydivkit/div/div_action_array_remove_value.py
pydivkit/div/div_action_array_set_value.py
pydivkit/div/div_action_clear_focus.py
pydivkit/div/div_action_copy_to_clipboard.py
pydivkit/div/div_action_copy_to_clipboard_content.py
pydivkit/div/div_action_custom.py
pydivkit/div/div_action_dict_set_value.py
pydivkit/div/div_action_download.py
pydivkit/div/div_action_focus_element.py
pydivkit/div/div_action_hide_tooltip.py
pydivkit/div/div_action_scroll_by.py
pydivkit/div/div_action_scroll_destination.py
pydivkit/div/div_action_scroll_to.py
pydivkit/div/div_action_set_state.py
pydivkit/div/div_action_set_stored_value.py
pydivkit/div/div_action_set_variable.py
pydivkit/div/div_action_show_tooltip.py
pydivkit/div/div_action_submit.py
pydivkit/div/div_action_timer.py
pydivkit/div/div_action_typed.py
pydivkit/div/div_action_update_structure.py
pydivkit/div/div_action_video.py
pydivkit/div/div_alignment_horizontal.py
pydivkit/div/div_alignment_vertical.py
pydivkit/div/div_animation.py
pydivkit/div/div_animation_direction.py
pydivkit/div/div_animation_interpolator.py
pydivkit/div/div_animator.py
pydivkit/div/div_animator_base.py
pydivkit/div/div_appearance_set_transition.py
pydivkit/div/div_appearance_transition.py
pydivkit-32.34.0.dist-info/METADATA
pydivkit-32.34.0.dist-info/WHEEL
pydivkit-32.34.0.dist-info/RECORD
